experiment_config_agent/__init__.py
experiment_config_agent/agent.py
experiment_config_agent/config.py
experiment_config_agent/constants.py
experiment_config_agent/models.py
experiment_configuration_agent-0.1.4.dist-info/METADATA
experiment_configuration_agent-0.1.4.dist-info/WHEEL
experiment_configuration_agent-0.1.4.dist-info/top_level.txt
experiment_configuration_agent-0.1.4.dist-info/RECORD
