Metadata-Version: 2.4
Name: experiment-configuration-agent
Version: 0.1.4
Summary: Add your description here
Requires-Python: >=3.10
Requires-Dist: pydantic-settings
Requires-Dist: sfn-blueprint>=0.6.21
Provides-Extra: dev
Requires-Dist: pytest; extra == "dev"
Requires-Dist: pytest-mock; extra == "dev"
